LICENSE.txt
README.md
setup.py
simple_xml_to_json/__init__.py
simple_xml_to_json/simple_xml_to_json.py
simple_xml_to_json.egg-info/PKG-INFO
simple_xml_to_json.egg-info/SOURCES.txt
simple_xml_to_json.egg-info/dependency_links.txt
simple_xml_to_json.egg-info/requires.txt
simple_xml_to_json.egg-info/top_level.txt