Metadata-Version: 2.4
Name: simple-xml-to-json
Version: 0.0.2
Summary: A simple xml to json converter
Author: Christopher Abanilla
License: MIT
License-File: LICENSE.txt
Requires-Dist: lxml
Dynamic: author
Dynamic: description
Dynamic: description-content-type
Dynamic: license
Dynamic: license-file
Dynamic: requires-dist
Dynamic: summary
